hnmp.py
hnmp-0.5.1.dist-info/DESCRIPTION.rst
hnmp-0.5.1.dist-info/METADATA
hnmp-0.5.1.dist-info/metadata.json
hnmp-0.5.1.dist-info/RECORD
hnmp-0.5.1.dist-info/top_level.txt
hnmp-0.5.1.dist-info/WHEEL
