Metadata-Version: 2.0
Name: hnmp
Version: 0.5.1
Summary: High-level Python SNMP library
Home-page: https://github.com/trehn/hnmp
Author: Torsten Rehn
Author-email: torsten@rehn.email
License: ISC
Keywords: SNMP,OID,MIB
Platform: UNKNOWN
Classifier: Development Status :: 4 - Beta
Classifier: Intended Audience :: Developers
Classifier: Intended Audience :: System Administrators
Classifier: License :: OSI Approved :: ISC License (ISCL)
Classifier: Operating System :: MacOS :: MacOS X
Classifier: Operating System :: POSIX
Classifier: Operating System :: Unix
Classifier: Programming Language :: Python :: 2.7
Classifier: Programming Language :: Python :: 3
Classifier: Topic :: Software Development :: Libraries :: Python Modules
Classifier: Topic :: System :: Hardware
Classifier: Topic :: System :: Monitoring
Requires-Dist: pysnmp (>=4.2.1)
